Pjono/Cookie.py
Pjono/Debug.py
Pjono/Response.py
Pjono/Server.py
Pjono/__init__.py
Pjono/mime.json
Pjono/PAGES/404.html
Pjono/PAGES/error.html
Pjono/PAGES/error1.html
Pjono/PAGES/start.html
Pjono/PAGES/Assets/icon.png
Pjono/PARSE/Components.py
Pjono/PARSE/Html.py
Pjono/PARSE/__init__.py
Pjono/PARSE/ascii.json
Pjono/PARSE/parse.py
Pjono/Signal/__init__.py
Pjono/Signal/signal.js
Pjono/Signal/signal.py
Pjono-0.0.4.dist-info/LICENSE
Pjono-0.0.4.dist-info/METADATA
Pjono-0.0.4.dist-info/WHEEL
Pjono-0.0.4.dist-info/top_level.txt
Pjono-0.0.4.dist-info/RECORD
