Metadata-Version: 2.1
Name: Pjono
Version: 0.0.4
Summary: a Web Framework made by Xp-op
Home-page: https://github.com/Xp-op/Pjono
Author: Xp-op
Author-email: muhammad184276@gmail.com
License: UNKNOWN
Project-URL: Documentation, https://github.com/Xp-op/Pjono/wiki/Documention
Project-URL: Bug Tracker, https://github.com/Xp-op/Pjono/issues
Platform: UNKNOWN
Classifier: Programming Language :: Python :: 3
Classifier: License :: OSI Approved :: MIT License
Classifier: Operating System :: OS Independent
Requires-Python: >=3.6
License-File: LICENSE
